hi_tbongkim03/__init__.py
hi_tbongkim03/hello.py
hi_tbongkim03-0.8.0.dist-info/METADATA
hi_tbongkim03-0.8.0.dist-info/WHEEL
hi_tbongkim03-0.8.0.dist-info/entry_points.txt
hi_tbongkim03-0.8.0.dist-info/top_level.txt
hi_tbongkim03-0.8.0.dist-info/RECORD
