Metadata-Version: 2.1
Name: hi_tbongkim03
Version: 0.8.0
Summary: Default template for PDM package
Author-email: tbongkim03 <tbongkim03@gmial.com>
License: MIT
Requires-Python: ==3.12.*
